{
    "id": 3038,
    "name": "julian level",
    "description": "A rainbow insane demon with awkward timings, ending off with an intense cube and ball dual. There are also cats afoot.",
    "gdleveldescription": "dedicated to julian, my brother. verified by finn. 1026 attempts.",
    "author": "finn",
    "creators": ["finn"],
    "verifier": "finn",
    "verification": "https://youtu.be/mVRjGF2QIic?si=b2_TYETmv8RKvbSX",
    "showcase": "https://youtu.be/mVRjGF2QIic?si=b2_TYETmv8RKvbSX",
    "percentToQualify": 74,
    "records": [
      {
          "user": "Raezori",
          "link": "https://youtu.be/VeeLtCIvhgM",
          "percent": 100
      }
    ]
}
